xeofs/__init__.py
xeofs/_version.py
xeofs/base_model.py
xeofs/rotator_factory.py
xeofs/cross/__init__.py
xeofs/cross/base_model_cross_set.py
xeofs/cross/cca.py
xeofs/cross/cpcca.py
xeofs/cross/cpcca_rotator.py
xeofs/cross/mca.py
xeofs/cross/mca_rotator.py
xeofs/cross/rda.py
xeofs/data_container/__init__.py
xeofs/data_container/data_container.py
xeofs/linalg/__init__.py
xeofs/linalg/decomposer.py
xeofs/linalg/rotation.py
xeofs/linalg/svd.py
xeofs/linalg/utils.py
xeofs/linalg/_numpy/__init__.py
xeofs/linalg/_numpy/_rotation.py
xeofs/linalg/_numpy/_svd.py
xeofs/linalg/_numpy/_utils.py
xeofs/multi/__init__.py
xeofs/multi/cca.py
xeofs/preprocessing/__init__.py
xeofs/preprocessing/concatenator.py
xeofs/preprocessing/dimension_renamer.py
xeofs/preprocessing/list_processor.py
xeofs/preprocessing/multi_index_converter.py
xeofs/preprocessing/pca.py
xeofs/preprocessing/preprocessor.py
xeofs/preprocessing/sanitizer.py
xeofs/preprocessing/scaler.py
xeofs/preprocessing/stacker.py
xeofs/preprocessing/transformer.py
xeofs/preprocessing/whitener.py
xeofs/single/__init__.py
xeofs/single/base_model_single_set.py
xeofs/single/eeof.py
xeofs/single/eof.py
xeofs/single/eof_rotator.py
xeofs/single/gwpca.py
xeofs/single/opa.py
xeofs/single/pop.py
xeofs/single/sparse_pca.py
xeofs/single/_numpy/__init__.py
xeofs/single/_numpy/_sparse_pca.py
xeofs/utils/__init__.py
xeofs/utils/constants.py
xeofs/utils/data_types.py
xeofs/utils/dimension_renamer.py
xeofs/utils/hilbert_transform.py
xeofs/utils/io.py
xeofs/utils/sanity_checks.py
xeofs/utils/xarray_utils.py
xeofs/utils/optional/__init__.py
xeofs/utils/optional/distance_metrics.py
xeofs/utils/optional/kernels.py
xeofs/utils/optional/numba_utils.py
xeofs/utils/optional/statistics.py
xeofs/validation/__init__.py
xeofs/validation/_base_bootstrapper.py
xeofs/validation/bootstrapper.py
xeofs-3.0.4.dist-info/LICENSE
xeofs-3.0.4.dist-info/METADATA
xeofs-3.0.4.dist-info/WHEEL
xeofs-3.0.4.dist-info/top_level.txt
xeofs-3.0.4.dist-info/RECORD
