Metadata-Version: 2.1
Name: xeofs
Version: 3.0.4
Summary: Comprehensive EOF analysis in Python with xarray: A versatile, multidimensional, and scalable tool for advanced climate data analysis
Author-email: Niclas Rieger <niclasrieger@gmail.com>, "Samuel J. Levang" <slevang@gmail.com>
License: MIT
Project-URL: homepage, https://github.com/xarray-contrib/xeofs
Project-URL: repository, https://github.com/xarray-contrib/xeofs
Project-URL: documentation, https://xeofs.readthedocs.io/en/latest/
Requires-Python: >=3.10
License-File: LICENSE
Requires-Dist: numpy>=1.24
Requires-Dist: pandas>=2
Requires-Dist: xarray>=2024.10.0
Requires-Dist: scikit-learn>=1.0.2
Requires-Dist: tqdm>=4.64.0
Requires-Dist: dask>=2023.0.1
Requires-Dist: typing-extensions>=4.8.0
Provides-Extra: complete
Requires-Dist: xeofs[etc,io]; extra == "complete"
Provides-Extra: dev
Requires-Dist: build>=1.0.0; extra == "dev"
Requires-Dist: ruff>=0.3; extra == "dev"
Requires-Dist: pytest>=7; extra == "dev"
Requires-Dist: pytest-xdist>=3; extra == "dev"
Requires-Dist: coverage>=6; extra == "dev"
Requires-Dist: pre-commit>=3; extra == "dev"
Requires-Dist: nbstripout>=0.6; extra == "dev"
Requires-Dist: pooch>=1.6.0; extra == "dev"
Provides-Extra: docs
Requires-Dist: rpy2>=3.5; extra == "docs"
Requires-Dist: sphinx-gallery>=0.14; extra == "docs"
Requires-Dist: sphinx-design>=0.6; extra == "docs"
Requires-Dist: sphinx-copybutton>=0.5; extra == "docs"
Requires-Dist: nbsphinx>=0.9; extra == "docs"
Requires-Dist: pydata-sphinx-theme>=0.15; extra == "docs"
Requires-Dist: sphinx>=8; extra == "docs"
Requires-Dist: nbconvert>=7.9; extra == "docs"
Requires-Dist: myst-parser>=3.0; extra == "docs"
Requires-Dist: matplotlib>=3.4; extra == "docs"
Requires-Dist: seaborn>=0.11; extra == "docs"
Requires-Dist: cartopy>=0.22; extra == "docs"
Requires-Dist: pooch>=1.6.0; extra == "docs"
Requires-Dist: ipython>=8.14; extra == "docs"
Requires-Dist: ipykernel>=6.23; extra == "docs"
Provides-Extra: etc
Requires-Dist: numba>=0.57; extra == "etc"
Requires-Dist: statsmodels>=0.14.0; extra == "etc"
Provides-Extra: io
Requires-Dist: h5netcdf>=1.0.0; extra == "io"
Requires-Dist: netcdf4>=1.5.8; extra == "io"
Requires-Dist: zarr>=2.14.0; extra == "io"
